setup.py
libms/__init__.py
libms/db.py
libms/infodict.py
libms/newznab.py
libms/sabnzbd.py
movie_search_lib.egg-info/PKG-INFO
movie_search_lib.egg-info/SOURCES.txt
movie_search_lib.egg-info/dependency_links.txt
movie_search_lib.egg-info/requires.txt
movie_search_lib.egg-info/top_level.txt