Metadata-Version: 2.1
Name: movie-search-lib
Version: 0.1.9
Summary: Get results of movie searches
Home-page: UNKNOWN
Author: Jay Deiman
Author-email: admin@splitstreams.com
License: UNKNOWN
Platform: UNKNOWN
Classifier: Development Status :: 4 - Beta
Classifier: Environment :: Console
Classifier: Intended Audience :: System Administrators
Classifier: License :: OSI Approved :: GNU General Public License v2 (GPLv2)
Classifier: Natural Language :: English
Classifier: Topic :: Internet :: Name Service (DNS)
Classifier: Operating System :: POSIX
Classifier: Programming Language :: Python
Classifier: Topic :: System :: Systems Administration
